phial/__init__.py
phial/bot.py
phial/commands.py
phial/errors.py
phial/globals.py
phial/py.typed
phial/scheduler.py
phial/utils.py
phial/wrappers.py
phial_slack-0.12.2.dist-info/LICENSE
phial_slack-0.12.2.dist-info/METADATA
phial_slack-0.12.2.dist-info/WHEEL
phial_slack-0.12.2.dist-info/top_level.txt
phial_slack-0.12.2.dist-info/RECORD
