Metadata-Version: 2.2
Name: phial-slack
Version: 0.12.2
Summary: A Slack bot framework
Author-email: James Seden Smith <sedders123@gmail.com>
Maintainer-email: James Seden Smith <sedders123@gmail.com>
Project-URL: Homepage, https://github.com/sedders123/phial/
Project-URL: Documentation, https://phial.dev/
Project-URL: Source, https://github.com/sedders123/phial/
Project-URL: Issues, https://github.com/sedders123/phial/issues
Keywords: slack,bot,framework,phial,slackbot
Classifier: Development Status :: 3 - Alpha
Classifier: License :: OSI Approved :: MIT License
Classifier: Intended Audience :: Developers
Classifier: Operating System :: OS Independent
Classifier: Programming Language :: Python
Classifier: Programming Language :: Python :: 3 :: Only
Classifier: Topic :: Software Development :: Libraries :: Python Modules
Classifier: Typing :: Typed
Requires-Python: >=3.11
License-File: LICENSE
Requires-Dist: slack-sdk>=3.34.0
Requires-Dist: werkzeug>=3.1.3
